MANIFEST.in
README.md
setup.py
version.txt
odintools/__init__.py
odintools/args.py
odintools/commands.py
odintools/constants.py
odintools/validators.py
odintools.egg-info/PKG-INFO
odintools.egg-info/SOURCES.txt
odintools.egg-info/dependency_links.txt
odintools.egg-info/entry_points.txt
odintools.egg-info/requires.txt
odintools.egg-info/top_level.txt