Metadata-Version: 1.0
Name: odintools
Version: 0.2.4
Summary: Odin setuptools extensions
Home-page: http://aps.odin.com
Author: apsliteteam
Author-email: aps@odin.com
License: Other/Proprietary License
Keywords: setup,distutils
Platform: UNKNOWN
Classifier: License :: Other/Proprietary License
Classifier: Programming Language :: Python :: 2
Classifier: Programming Language :: Python :: 2.6
Classifier: Programming Language :: Python :: 2.7
Classifier: Programming Language :: Python :: 3
Classifier: Programming Language :: Python :: 3.4
Classifier: Programming Language :: Python :: 3.5
